morseify/__init__.py
morseify/__main__.py
morseify/cli.py
morseify/core.py
morseify/explain.py
morseify/mapping.py
morseify/normalize.py
morseify/quiz.py
morseify_lumen-0.1.2.dist-info/licenses/LICENSE
morseify_lumen-0.1.2.dist-info/METADATA
morseify_lumen-0.1.2.dist-info/WHEEL
morseify_lumen-0.1.2.dist-info/entry_points.txt
morseify_lumen-0.1.2.dist-info/top_level.txt
morseify_lumen-0.1.2.dist-info/RECORD
