Metadata-Version: 2.4
Name: morseify-lumen
Version: 0.1.2
Summary: A Python package for encoding and decoding Morse code.
Author: Team Lumen
License:                     GNU GENERAL PUBLIC LICENSE
Project-URL: Homepage, https://github.com/swe-students-fall2025/3-python-package-team_lumen
Project-URL: Issues, https://github.com/swe-students-fall2025/3-python-package-team_lumen/issues
Keywords: python,morse code,encoder,decoder
Classifier: Programming Language :: Python :: 3
Classifier: License :: OSI Approved :: MIT License
Classifier: Operating System :: OS Independent
Requires-Python: >=3.10
License-File: LICENSE
Dynamic: license-file
